xignitegh/__init__.py
xignitegh/xignitegh.py
xignitegh-0.2.1.dist-info/LICENSE
xignitegh-0.2.1.dist-info/METADATA
xignitegh-0.2.1.dist-info/WHEEL
xignitegh-0.2.1.dist-info/top_level.txt
xignitegh-0.2.1.dist-info/RECORD
