Metadata-Version: 2.1
Name: xignitegh
Version: 0.2.1
Summary: A wrapper to the XigniteGlobalHistorical API
Home-page: https://github.com/xignite-python/xignitegh
Author: Kapitalisman
Author-email: hallo@kapitalisman.nl
License: MIT
Keywords: xignite api wrapper
Platform: UNKNOWN
Classifier: Development Status :: 3 - Alpha
Classifier: License :: OSI Approved :: MIT License
Classifier: Programming Language :: Python :: 3.7
Requires-Python: >=3
License-File: LICENSE
Requires-Dist: requests (>=2)
